django_chili/__init__.py
django_chili/bowl.py
django_chili/chop.py
django_chili/chunk.py
django_chili/sauce.py
django_chili-0.1.0.dev3.dist-info/METADATA
django_chili-0.1.0.dev3.dist-info/WHEEL
django_chili-0.1.0.dev3.dist-info/top_level.txt
django_chili-0.1.0.dev3.dist-info/RECORD
