Metadata-Version: 2.1
Name: django-chili
Version: 0.1.0.dev3
Summary: Using static HTML files as templates with Django projects.
Author-email: Sean O'Dell <sean@celsoft.com>
Project-URL: Documentation, https://docs.django-chili.io/
Project-URL: Source, https://github.com/django-chili/django-chili
Classifier: Programming Language :: Python :: 3
Classifier: License :: OSI Approved :: MIT License
Classifier: Operating System :: OS Independent
Requires-Python: >=3.7
Requires-Dist: django <6,>=5.0
Requires-Dist: jinja2 <4,>=3.0
Requires-Dist: beautifulsoup4 <5,>=4.11
